parametric_plasma_source.libs/libhdf5_hl-2c30fab8.so.8.0.1
parametric_plasma_source.libs/libhdf5-8f9b6202.so.8.0.1
parametric_plasma_source.libs/libgfortran-040039e1.so.5.0.0
parametric_plasma_source.libs/libgomp-7c85b1e2.so.1.0.0
parametric_plasma_source.libs/libz-d8a329de.so.1.2.7
parametric_plasma_source.libs/libaec-dda3378b.so.0.0.10
parametric_plasma_source.libs/libopenmc-74ff0278.so
parametric_plasma_source.libs/libsz-fcfb8163.so.2.0.1
parametric_plasma_source.libs/libquadmath-30d679e1.so.0.0.0
parametric_plasma_source-0.0.8.dist-info/RECORD
parametric_plasma_source-0.0.8.dist-info/METADATA
parametric_plasma_source-0.0.8.dist-info/top_level.txt
parametric_plasma_source-0.0.8.dist-info/WHEEL
parametric_plasma_source-0.0.8.dist-info/LICENSE
parametric_plasma_source/plasma_source.cpython-38-x86_64-linux-gnu.so
parametric_plasma_source/__init__.py
parametric_plasma_source/libpugixml.a
parametric_plasma_source/source_sampling.so
