Metadata-Version: 2.1
Name: parametric-plasma-source
Version: 0.0.8
Summary: Parametric plasma source for fusion simulations in OpenMC
Home-page: https://github.com/makeclean/parametric-plasma-source/
Author: Andrew Davis
Author-email: jonathan.shimwell@ukaea.uk
License: UNKNOWN
Platform: UNKNOWN
Classifier: Programming Language :: Python :: 3
Classifier: License :: OSI Approved :: MIT License
Classifier: Operating System :: OS Independent
